{
    "title": "REC 2",
    "pelicula": "REC 2",
    "director": "Desconocido",
    "url": "https://ghostintheblog.com/2009/11/rec-2.html",
    "date": "2009-11-22T02:09:00+01:00",
    "content": "Título Original: REC 2 Dirección y guión: aume Balagueró y Paco Plaza Intérpretes: Jonathan Mellor, Óscar Sánchez Zafra, Ariel Casas, Alejandro Casaseca, Pablo Rosso, Pep Molina y Andrea Ros Nacionalidad: España. 2009 Duración: 85 minutos ESTRENO: noviembre 2009\n\nCRÍTICA:\nLo que empezó como una huida hacia adelante motivada por una situación de cierto desánimo, REC, ha terminado por representar la cumbre española del género a lo largo de lo que llevamos del siglo XXI, lo cual resulta paradójico: ese díptico formado por REC y REC 2."
}