{
    "title": "TODAS LAS CANCIONES HABLAN DE MÍ",
    "pelicula": "TODAS LAS CANCIONES HABLAN DE MÍ",
    "director": "Desconocido",
    "url": "https://ghostintheblog.com/2010/12/todas-las-canciones-hablan-de-mi.html",
    "date": "2010-12-16T19:04:00+01:00",
    "content": "Título Original: TODAS LAS CANCIONES HABLAN DE MÍ Dirección: Jonás Trueba Guión: Jonás Trueba y Daniel Gascón Intérpretes: Oriol Vila, Bárbara Lennie, Ramón Fontserè, Bruno Bergonzini, Valeria Alonso, Ángela Cremonte y Miriam Giovanelli Nacionalidad: España. 2010 Duración: 107 minutos ESTRENO: Diciembre 2010\n\nCRÍTICA:\n"
}